{
    "series": [
        {
            "name": "物业费收缴分析",
            "items": [
                50000,
                45000,
                47000,
                44000,
                46000,
                61000,
                54000,
                46000,
                42000,
                54000,
                52000,
                50000
            ]
        },
        {
            "name": "水电损耗",
            "items": [
                1000,
                0,
                200,
                1000,
                3000,
                6000,
                1000,
                2600,
                4200,
                5400,
                5200,
                5000
            ]
        }
    ],
    "groups": [
        "1",
        "2",
        "3",
        "4",
        "5",
        "6",
        "7",
        "8",
        "9",
        "10",
        "11",
        "12"
    ]
}